WeixinGongzhongPingtaiKaifaWendang/README.md
WeixinGongzhongPingtaiKaifaWendang/__init__.py
WeixinGongzhongPingtaiKaifaWendang/__main__.py
WeixinGongzhongPingtaiKaifaWendang/file.epub
WeixinGongzhongPingtaiKaifaWendang/index.html
WeixinGongzhongPingtaiKaifaWendang/css/__init__.py
WeixinGongzhongPingtaiKaifaWendang/css/annotations.css
WeixinGongzhongPingtaiKaifaWendang/css/main.css
WeixinGongzhongPingtaiKaifaWendang/css/normalize.css
WeixinGongzhongPingtaiKaifaWendang/css/popup.css
WeixinGongzhongPingtaiKaifaWendang/font/__init__.py
WeixinGongzhongPingtaiKaifaWendang/font/fontello.eot
WeixinGongzhongPingtaiKaifaWendang/font/fontello.svg
WeixinGongzhongPingtaiKaifaWendang/font/fontello.ttf
WeixinGongzhongPingtaiKaifaWendang/font/fontello.woff
WeixinGongzhongPingtaiKaifaWendang/img/__init__.py
WeixinGongzhongPingtaiKaifaWendang/img/annotator-glyph-sprite.png
WeixinGongzhongPingtaiKaifaWendang/img/annotator-icon-sprite.png
WeixinGongzhongPingtaiKaifaWendang/img/apple-touch-icon.png
WeixinGongzhongPingtaiKaifaWendang/img/cancelfullscreen.png
WeixinGongzhongPingtaiKaifaWendang/img/close.png
WeixinGongzhongPingtaiKaifaWendang/img/fullscreen.png
WeixinGongzhongPingtaiKaifaWendang/img/loader.gif
WeixinGongzhongPingtaiKaifaWendang/img/menu-icon.png
WeixinGongzhongPingtaiKaifaWendang/img/save.png
WeixinGongzhongPingtaiKaifaWendang/img/saved.png
WeixinGongzhongPingtaiKaifaWendang/img/settings-s.png
WeixinGongzhongPingtaiKaifaWendang/img/settings.png
WeixinGongzhongPingtaiKaifaWendang/img/star.png
WeixinGongzhongPingtaiKaifaWendang/js/__init__.py
WeixinGongzhongPingtaiKaifaWendang/js/epub.js
WeixinGongzhongPingtaiKaifaWendang/js/epub.min.js
WeixinGongzhongPingtaiKaifaWendang/js/epub.min.map
WeixinGongzhongPingtaiKaifaWendang/js/hooks.min.js
WeixinGongzhongPingtaiKaifaWendang/js/hooks.min.map
WeixinGongzhongPingtaiKaifaWendang/js/reader.js
WeixinGongzhongPingtaiKaifaWendang/js/reader.js.map
WeixinGongzhongPingtaiKaifaWendang/js/reader.min.js
weixin_gongzhong_pingtai_kaifa_wendang-2024.3.2.0.dist-info/METADATA
weixin_gongzhong_pingtai_kaifa_wendang-2024.3.2.0.dist-info/WHEEL
weixin_gongzhong_pingtai_kaifa_wendang-2024.3.2.0.dist-info/entry_points.txt
weixin_gongzhong_pingtai_kaifa_wendang-2024.3.2.0.dist-info/top_level.txt
weixin_gongzhong_pingtai_kaifa_wendang-2024.3.2.0.dist-info/RECORD
